realeyes/emotion_detection/libNativeEmotionsLibrary.so
realeyes/emotion_detection/cpp.cpython-37m-x86_64-linux-gnu.so
realeyes/emotion_detection/__init__.py
realeyes.emotion_detection-2.7.4.dist-info/WHEEL
realeyes.emotion_detection-2.7.4.dist-info/top_level.txt
realeyes.emotion_detection-2.7.4.dist-info/RECORD
realeyes.emotion_detection-2.7.4.dist-info/METADATA
