Metadata-Version: 2.1
Name: realeyes.emotion-detection
Version: 2.7.4
Summary: Emotion Detection library from RealEyes
Home-page: https://developers.realeyesit.com/NEL/index.html
Author: Realeyes
Author-email: daniel@realeyesit.com
Requires-Dist: numpy >=1.10.0
